syringe.py
syringe-0.3.0.dist-info/RECORD
syringe-0.3.0.dist-info/metadata.json
syringe-0.3.0.dist-info/DESCRIPTION.rst
syringe-0.3.0.dist-info/zip-safe
syringe-0.3.0.dist-info/METADATA
syringe-0.3.0.dist-info/top_level.txt
syringe-0.3.0.dist-info/WHEEL
