Metadata-Version: 2.0
Name: syringe
Version: 0.3.0
Summary: A simple dependency injection library
Home-page: https://github.com/remcohaszing/python-syringe
Author: Remco Haszing
Author-email: remcohaszing@gmail.com
License: MIT
Platform: UNKNOWN
Provides-Extra: mock
Requires-Dist: mock; "2" in python_version and extra == 'mock'
